ewatercycle_HBV/__init__.py
ewatercycle_HBV/forcing.py
ewatercycle_HBV/model.py
ewatercycle_hbv-1.8.5.dist-info/METADATA
ewatercycle_hbv-1.8.5.dist-info/WHEEL
ewatercycle_hbv-1.8.5.dist-info/entry_points.txt
ewatercycle_hbv-1.8.5.dist-info/licenses/LICENSE.txt
ewatercycle_hbv-1.8.5.dist-info/RECORD
