Metadata-Version: 2.3
Name: ewatercycle-HBV
Version: 1.8.5
Summary: Implementation of HBV for eWaterCycle
Project-URL: homepage, https://github.com/Daafip/ewatercycle-hbv
Author-email: David Haasnoot <davidhaasnoot@gmail.com>
License-Expression: Apache-2.0
License-File: LICENSE.txt
Keywords: ewatercycle,hydrology
Classifier: Intended Audience :: Developers
Classifier: License :: OSI Approved :: Apache Software License
Classifier: Natural Language :: English
Classifier: Operating System :: OS Independent
Classifier: Programming Language :: Python
Classifier: Programming Language :: Python :: 3 :: Only
Requires-Dist: ewatercycle
